rest_invitations/__init__.py
rest_invitations/app_settings.py
rest_invitations/models.py
rest_invitations/serializers.py
rest_invitations/urls.py
rest_invitations/utils.py
rest_invitations/views.py
tests/__init__.py
tests/tests.py
django_rest_invitations-0.1.2.dist-info/LICENSE
django_rest_invitations-0.1.2.dist-info/METADATA
django_rest_invitations-0.1.2.dist-info/WHEEL
django_rest_invitations-0.1.2.dist-info/top_level.txt
django_rest_invitations-0.1.2.dist-info/RECORD
